Metadata-Version: 2.1
Name: StarTSPImage
Version: 0.2.3
Summary: Creates Star graphics mode raster images for use with Star TSP series thermal printers
Home-page: https://github.com/geftactics/python-StarTSPImage
Author: Geoff Kendal
Author-email: Geoff@squiggle.org
License: MIT
Download-URL: https://github.com/geftactics/python-StarTSPImage/archive/0.2.3.tar.gz
Platform: UNKNOWN
